{
  "lastUpdated": "2026-06-04T07:17:55.799691",
  "foehnWarning": true,
  "sections": [
    {
      "title": "Heute tagsüber",
      "content": ".\nWETTERLAGE\n:\nÖsterreich befindet sich im Einflussbereich eines schwachen\nZwischenhochs bei südwestlicher Höhenströmung. Ausläufer der nächsten\natlantischen\nKaltfront\nerreichen gegen Abend den Westen.\n.\nWETTERABLAUF FLUGWETTER:\nLokale\nNebel\n- und Hochnebelfelder in den Alpentälern sowie in den\nsüdlichen Beckenlagen lösen sich rasch auf. In weiterer Folge\ndominiert gutsichtiges Flugwetter mit lockerer, flacher\nQuellbewölkung über den Alpen. Im Tagesverlauf dreht die\nHöhenströmung dann zunehmend auf Südwest und in Teilen Oberkärntens\nsowie in Osttirol bildet sich Staubewölkung, die die Gipfel zunehmend\neinhüllt. In Vorarlberg und den westlichen Teilen Nordtirols ziehen\nspätnachmittags dichte Wolkenfelder mit deutlich absinkenden Basen\nauf, in der Folge ist hier mit kräftigen Regenschauern und auch dem\neinen oder anderen\nGewitter\nmit stürmischen Windböen zu rechnen.\nIm Osten, Süden und Südosten herrscht auch am Nachmittag gutes\nFlugwetter.\n.\nHINWEISE ZUR NULLGRADGRENZE:\nMeist um 10000ft amsl, im Norden und Osten föhnbedingt tagsüber um\n12000ft amsl.\n.\nHINWEISE WINDSYSTEME UND\nTURBULENZ\n:\nWestliche Höhenströmung, die im Tagesverlauf zunehmend auf Südwest\ndreht. Im Bergland aufkommender\nSüdföhn\nmit Turbulenzen in Kamm- und\nLeelagen. Am Alpenostrand zunehmender Südostwind, im Donauraum\nOstwind.\n.\nHINWEISE THERMISCHER FLUGSPORT UND WINDSEGELFLUG:\nThermisch aktive\nLuftmasse\n. In den alpennordseitigen Längstälern\nSüdwindunterstützung. Im Westen beendet in der zweiten Tageshälfte\neine\nKaltfront\ndie Flugbedingungen. In der Südwestströmung lokale\nWellenregime im Bereich des Alpenhauptkamms und der Südalpen.\n.\nHINWEISE BALLONFAHRTEN:\nIn der Früh oft windschwach, nur im Nordosten noch teils lebhafter\nNordwestwind. Am Abend anhaltender Südost- bis Südwind.\n.\nPROGNOSESICHERHEIT\nWETTERLAGE\n: abgesichert\nPROGNOSESICHERHEIT WETTERABLAUF: abgesichert\n.\nDetaillierte Vorhersagen über Höhenwind, Höhentemperaturen und QNH\nentnehmen Sie bitte unseren grafischen Vorhersagekarten.\nDiese Vorhersage wird bei abweichender aktueller Entwicklung nicht\nberichtigt.\n"
    }
  ],
  "forecast": "FLUGWETTERÜBERSICHT ÖSTERREICH,\nherausgegeben am Donnerstag, 04.06.2026 um 00:00 Uhr lct.\nVorhersage von heute Früh BCMT bis heute Abend ECET\n.\n\nWETTERLAGE\n:\nÖsterreich befindet sich im Einflussbereich eines schwachen\nZwischenhochs bei südwestlicher Höhenströmung. Ausläufer der nächsten\natlantischen \nKaltfront\n erreichen gegen Abend den Westen.\n.\nWETTERABLAUF FLUGWETTER:\nLokale \nNebel\n- und Hochnebelfelder in den Alpentälern sowie in den\nsüdlichen Beckenlagen lösen sich rasch auf. In weiterer Folge\ndominiert gutsichtiges Flugwetter mit lockerer, flacher\nQuellbewölkung über den Alpen. Im Tagesverlauf dreht die\nHöhenströmung dann zunehmend auf Südwest und in Teilen Oberkärntens\nsowie in Osttirol bildet sich Staubewölkung, die die Gipfel zunehmend\neinhüllt. In Vorarlberg und den westlichen Teilen Nordtirols ziehen\nspätnachmittags dichte Wolkenfelder mit deutlich absinkenden Basen\nauf, in der Folge ist hier mit kräftigen Regenschauern und auch dem\neinen oder anderen \nGewitter\n mit stürmischen Windböen zu rechnen.\nIm Osten, Süden und Südosten herrscht auch am Nachmittag gutes\nFlugwetter.\n.\nHINWEISE ZUR NULLGRADGRENZE:\nMeist um 10000ft amsl, im Norden und Osten föhnbedingt tagsüber um\n12000ft amsl.\n.\nHINWEISE WINDSYSTEME UND \nTURBULENZ\n:\nWestliche Höhenströmung, die im Tagesverlauf zunehmend auf Südwest\ndreht. Im Bergland aufkommender \nSüdföhn\n mit Turbulenzen in Kamm- und\nLeelagen. Am Alpenostrand zunehmender Südostwind, im Donauraum\nOstwind.\n.\nHINWEISE THERMISCHER FLUGSPORT UND WINDSEGELFLUG:\nThermisch aktive \nLuftmasse\n. In den alpennordseitigen Längstälern\nSüdwindunterstützung. Im Westen beendet in der zweiten Tageshälfte\neine \nKaltfront\n die Flugbedingungen. In der Südwestströmung lokale\nWellenregime im Bereich des Alpenhauptkamms und der Südalpen.\n.\nHINWEISE BALLONFAHRTEN:\nIn der Früh oft windschwach, nur im Nordosten noch teils lebhafter\nNordwestwind. Am Abend anhaltender Südost- bis Südwind.\n.\nPROGNOSESICHERHEIT \nWETTERLAGE\n: abgesichert\nPROGNOSESICHERHEIT WETTERABLAUF: abgesichert\n.\nDetaillierte Vorhersagen über Höhenwind, Höhentemperaturen und QNH\nentnehmen Sie bitte unseren grafischen Vorhersagekarten.\nDiese Vorhersage wird bei abweichender aktueller Entwicklung nicht\nberichtigt."
}