{
  "lastUpdated": "2026-04-10T01:48:42.259290",
  "foehnWarning": false,
  "sections": [
    {
      "title": "Heute tagsüber",
      "content": ".\nWETTERLAGE\n:\nBei kräftiger nordwestlicher Höhenströmung steuert ein kleinräumiges\nTief\nmit Warm- und\nKaltfront\nden Wetterablauf über Österreich.\n.\nWETTERABLAUF FLUGWETTER:\nAn der Alpennordseite startet der Tag mit kompakter\nBewölkung\nmit\nBasen zwischen 3000ft und 6000ft amsl. Damit einhergehend hohes\nVereisungspotential bis in FL180. Dazu regnet es zunächst von\nVorarlberg bis ins Wald- und Mostviertel. In der Osthälfte ist es\nanfangs bei dichter AC-\nBewölkung\nnoch niederschlagsfrei. Mit\nAbsinken\nder Wolkenbasen in den tiefen SC-Bereich setzt im Laufe des\nVormittages auch hier allmählich\nRegen\nein. In Teilen Ober- und\nNiederösterreichs kann es dabei anfangs bis 2000ft amsl auch\nschneien. In der zweiten Tageshälfte zieht sich der\nNiederschlag\nauf\nden Nordalpenbereich zurück und geht zunehmend in Schauercharakter\nüber. Diese können nachfolgend gebietsweise auch auf die\nAlpensüdseite übergreifen.\n.\nHINWEISE ZUR NULLGRADGRENZE:\nAnfangs im Osten stellenweise um 3000ft amsl, später auf 4000ft bis\n5000ft amsl ansteigend. Sonst in 5000ft bis 7000ft amsl, am höchsten\nin Vorarlberg.\n.\nHINWEISE WINDSYSTEME UND\nTURBULENZ\n:\nAn der Alpennordseite zunehmender West- bis Nordwestwind, mit Kamm-\nund Leelagenturbulenz entlang der Nördlichen Kalkalpen. Im Süden und\nOsten windschwach in den unteren Schichten, Nordwestwind oberhalb von\n6000 bis 7000ft amsl.\n.\nHINWEISE THERMISCHER FLUGSPORT UND WINDSEGELFLUG:\nAlpennordseitig bereits am Vormittag aufkommende Niederschläge.\nAlpensüdseitig nimmt die\nBewölkung\nim Verlaufe des Vormittags rasch\nzu und am Nachmittag greifen zudem ein paar\nSchauer\nüber.\n.\nHINWEISE BALLONFAHRTEN:\nAm Morgen bodennah windschwache Bedingungen. Tagsüber verbreitet\nleichte Niederschläge und nördlich der Alpen kräftiger Westwind.\n.\nPROGNOSESICHERHEIT\nWETTERLAGE\n: abgesichert\nPROGNOSESICHERHEIT WETTERABLAUF: abgesichert\n.\nDetaillierte Vorhersagen über Höhenwind, Höhentemperaturen und QNH\nentnehmen Sie bitte unseren grafischen Vorhersagekarten.\nDiese Vorhersage wird bei abweichender aktueller Entwicklung nicht\nberichtigt.\n"
    }
  ],
  "forecast": "FLUGWETTERÜBERSICHT ÖSTERREICH,\nherausgegeben am Freitag, 10.04.2026 um 00:00 Uhr lct.\nVorhersage von heute Früh BCMT bis heute Abend ECET\n.\n\nWETTERLAGE\n:\nBei kräftiger nordwestlicher Höhenströmung steuert ein kleinräumiges\n\nTief\n mit Warm- und \nKaltfront\n den Wetterablauf über Österreich.\n.\nWETTERABLAUF FLUGWETTER:\nAn der Alpennordseite startet der Tag mit kompakter \nBewölkung\n mit\nBasen zwischen 3000ft und 6000ft amsl. Damit einhergehend hohes\nVereisungspotential bis in FL180. Dazu regnet es zunächst von\nVorarlberg bis ins Wald- und Mostviertel. In der Osthälfte ist es\nanfangs bei dichter AC-\nBewölkung\n noch niederschlagsfrei. Mit \nAbsinken\n\nder Wolkenbasen in den tiefen SC-Bereich setzt im Laufe des\nVormittages auch hier allmählich \nRegen\n ein. In Teilen Ober- und\nNiederösterreichs kann es dabei anfangs bis 2000ft amsl auch\nschneien. In der zweiten Tageshälfte zieht sich der \nNiederschlag\n auf\nden Nordalpenbereich zurück und geht zunehmend in Schauercharakter\nüber. Diese können nachfolgend gebietsweise auch auf die\nAlpensüdseite übergreifen.\n.\nHINWEISE ZUR NULLGRADGRENZE:\nAnfangs im Osten stellenweise um 3000ft amsl, später auf 4000ft bis\n5000ft amsl ansteigend. Sonst in 5000ft bis 7000ft amsl, am höchsten\nin Vorarlberg.\n.\nHINWEISE WINDSYSTEME UND \nTURBULENZ\n:\nAn der Alpennordseite zunehmender West- bis Nordwestwind, mit Kamm-\nund Leelagenturbulenz entlang der Nördlichen Kalkalpen. Im Süden und\nOsten windschwach in den unteren Schichten, Nordwestwind oberhalb von\n6000 bis 7000ft amsl.\n.\nHINWEISE THERMISCHER FLUGSPORT UND WINDSEGELFLUG:\nAlpennordseitig bereits am Vormittag aufkommende Niederschläge.\nAlpensüdseitig nimmt die \nBewölkung\n im Verlaufe des Vormittags rasch\nzu und am Nachmittag greifen zudem ein paar \nSchauer\n über.\n.\nHINWEISE BALLONFAHRTEN:\nAm Morgen bodennah windschwache Bedingungen. Tagsüber verbreitet\nleichte Niederschläge und nördlich der Alpen kräftiger Westwind.\n.\nPROGNOSESICHERHEIT \nWETTERLAGE\n: abgesichert\nPROGNOSESICHERHEIT WETTERABLAUF: abgesichert\n.\nDetaillierte Vorhersagen über Höhenwind, Höhentemperaturen und QNH\nentnehmen Sie bitte unseren grafischen Vorhersagekarten.\nDiese Vorhersage wird bei abweichender aktueller Entwicklung nicht\nberichtigt."
}