{
  "lastUpdated": "2026-05-05T21:55:15.390051",
  "foehnWarning": true,
  "sections": [
    {
      "title": "Heute tagsüber",
      "content": ".\nWETTERLAGE\n:\nMit südwestlicher Höhenströmung werden zunehmend feuchtere und\nlabilere Luftmassen zu den Alpen geführt. Die kräftige\nSüdföhnströmung hält an.\n.\nWETTERABLAUF FLUGWETTER:\nDie kompakte Staubewölkung in Osttirol und Oberkärnten bleibt bis in\ndie Nacht hinein beständig, bis zum Abend kann es hier stellenweise\nauch noch leicht regnen, Schneefallgrenze in etwa 7500ft amsl, lokal\nbesteht Vereisungsgefahr. Über die übrigen Regionen ziehen mittelhohe\nund hohe Wolkenfelder. Gegen Abend bis in die erste Nachthälfte\nhinein können sich dann in den Vorarlberger und Nordtiroler Nordalpen\nsowie in Oberösterreich vorübergehend einzelne\nSchauer\noder\nGewitter\nentwickeln. Tops bis FL320.\n.\nHINWEISE ZUR NULLGRADGRENZE:\n8500-10500ft amsl.\n.\nHINWEISE WINDSYSTEME UND\nTURBULENZ\n:\nLebhafter\nSüdföhn\nmit böigen Süd- bis Südwestwinden, Rotoren und\nteils erheblichen Kamm- und Leeturbulenzen. Ab den Abendstunden\nschieben sich unterhalb 8-10000ft amsl kräftige Westwinde darunter.\n.\nHINWEISE BALLONFAHRTEN:\nVerbreitet teils deutlich zu starke Bodenwinde.\n.\nPROGNOSESICHERHEIT\nWETTERLAGE\n: abgesichert\nPROGNOSESICHERHEIT WETTERABLAUF: abgesichert\n.\nDetaillierte Vorhersagen über Höhenwind, Höhentemperaturen und QNH\nentnehmen Sie bitte unseren grafischen Vorhersagekarten.\nDiese Vorhersage wird bei abweichender aktueller Entwicklung nicht\nberichtigt.\n"
    }
  ],
  "forecast": "FLUGWETTERÜBERSICHT ÖSTERREICH,\nherausgegeben am Dienstag, 05.05.2026 um 14:00 Uhr lct.\nVorhersage von heute Nachmittag bis morgen Früh BCMT\n.\n\nWETTERLAGE\n:\nMit südwestlicher Höhenströmung werden zunehmend feuchtere und\nlabilere Luftmassen zu den Alpen geführt. Die kräftige\nSüdföhnströmung hält an.\n.\nWETTERABLAUF FLUGWETTER:\nDie kompakte Staubewölkung in Osttirol und Oberkärnten bleibt bis in\ndie Nacht hinein beständig, bis zum Abend kann es hier stellenweise\nauch noch leicht regnen, Schneefallgrenze in etwa 7500ft amsl, lokal\nbesteht Vereisungsgefahr. Über die übrigen Regionen ziehen mittelhohe\nund hohe Wolkenfelder. Gegen Abend bis in die erste Nachthälfte\nhinein können sich dann in den Vorarlberger und Nordtiroler Nordalpen\nsowie in Oberösterreich vorübergehend einzelne \nSchauer\n oder \nGewitter\n\nentwickeln. Tops bis FL320.\n.\nHINWEISE ZUR NULLGRADGRENZE:\n8500-10500ft amsl.\n.\nHINWEISE WINDSYSTEME UND \nTURBULENZ\n:\nLebhafter \nSüdföhn\n mit böigen Süd- bis Südwestwinden, Rotoren und\nteils erheblichen Kamm- und Leeturbulenzen. Ab den Abendstunden\nschieben sich unterhalb 8-10000ft amsl kräftige Westwinde darunter.\n.\nHINWEISE BALLONFAHRTEN:\nVerbreitet teils deutlich zu starke Bodenwinde.\n.\nPROGNOSESICHERHEIT \nWETTERLAGE\n: abgesichert\nPROGNOSESICHERHEIT WETTERABLAUF: abgesichert\n.\nDetaillierte Vorhersagen über Höhenwind, Höhentemperaturen und QNH\nentnehmen Sie bitte unseren grafischen Vorhersagekarten.\nDiese Vorhersage wird bei abweichender aktueller Entwicklung nicht\nberichtigt."
}