{
  "lastUpdated": "2026-06-29T12:58:40.744636",
  "foehnWarning": false,
  "sections": [
    {
      "title": "Heute tagsüber",
      "content": ".\nWETTERLAGE\n:\nDer Hochschwerpunkt verlagert sich allmählich ostwärts. Die\nLuftmasse\nbleibt hochlabil und im Osten extrem heiß.\n.\nWETTERABLAUF FLUGWETTER:\nAm Nachmittag entstehen im gesamten Berg- und Hügelland mit Ausnahme\ndes Südostens verbreitet teils heftige\nGewitter\n, die sich\nclusterförmig organisieren und nur langsam nordostwärts ziehen.\nIsolierte\nCB\nsind auch entlang des Alpenostrands bis Wienerwald\nmöglich. Tops bis FL440. Hagelschlag kann ebenfalls ein Thema sein.\nMit den Gewittern sind kräftige Böen möglich, im Wiener Becken aus\nNordwest. In der ersten Nachthälfte beruhigt sich die\nGewitteraktivität bald. Nachfolgend bilden sich\nNebel\n- und\nHochnebelfelder, vor allem zwischen Tiroler Unterland und\nWaldviertel.\n.\nHINWEISE ZUR NULLGRADGRENZE:\nUm FL130.\n.\nHINWEISE WINDSYSTEME UND\nTURBULENZ\n:\nIn der Höhe dominieren weiterhin schwache südliche bis südwestliche\nWinde. In Gewitternähe stürmische Böen, vom Waldviertel bis Wiener\nBecken aus Nordwest auffrischend und in der Nacht anhaltend.\n.\nHINWEISE BALLONFAHRTEN:\nAm Abend verbreitet gestörtes Windfeld durch Gewitterböen. Morgen\nfrüh Nebelfelder, wo es zuvor gewittert hat. Im Osten anhaltender\nNordwestwind.\n.\nPROGNOSESICHERHEIT\nWETTERLAGE\n: abgesichert\nPROGNOSESICHERHEIT WETTERABLAUF: eher abgesichert\n.\nKOMMENTAR ZUR PROGNOSESICHERHEIT:\nUnklar bleibt, ob es auch ganz im Osten zu Gewitterbildungen kommt.\n.\nDetaillierte Vorhersagen über Höhenwind, Höhentemperaturen und QNH\nentnehmen Sie bitte unseren grafischen Vorhersagekarten.\nDiese Vorhersage wird bei abweichender aktueller Entwicklung nicht\nberichtigt.\n"
    }
  ],
  "forecast": "FLUGWETTERÜBERSICHT ÖSTERREICH,\nherausgegeben am Montag, 29.06.2026 um 14:00 Uhr lct.\nVorhersage von heute Nachmittag bis morgen Früh BCMT\n.\n\nWETTERLAGE\n:\nDer Hochschwerpunkt verlagert sich allmählich ostwärts. Die \nLuftmasse\n\nbleibt hochlabil und im Osten extrem heiß.\n.\nWETTERABLAUF FLUGWETTER:\nAm Nachmittag entstehen im gesamten Berg- und Hügelland mit Ausnahme\ndes Südostens verbreitet teils heftige \nGewitter\n, die sich\nclusterförmig organisieren und nur langsam nordostwärts ziehen.\nIsolierte \nCB\n sind auch entlang des Alpenostrands bis Wienerwald\nmöglich. Tops bis FL440. Hagelschlag kann ebenfalls ein Thema sein.\nMit den Gewittern sind kräftige Böen möglich, im Wiener Becken aus\nNordwest. In der ersten Nachthälfte beruhigt sich die\nGewitteraktivität bald. Nachfolgend bilden sich \nNebel\n- und\nHochnebelfelder, vor allem zwischen Tiroler Unterland und\nWaldviertel.\n.\nHINWEISE ZUR NULLGRADGRENZE:\nUm FL130.\n.\nHINWEISE WINDSYSTEME UND \nTURBULENZ\n:\nIn der Höhe dominieren weiterhin schwache südliche bis südwestliche\nWinde. In Gewitternähe stürmische Böen, vom Waldviertel bis Wiener\nBecken aus Nordwest auffrischend und in der Nacht anhaltend.\n.\nHINWEISE BALLONFAHRTEN:\nAm Abend verbreitet gestörtes Windfeld durch Gewitterböen. Morgen\nfrüh Nebelfelder, wo es zuvor gewittert hat. Im Osten anhaltender\nNordwestwind.\n.\nPROGNOSESICHERHEIT \nWETTERLAGE\n: abgesichert\nPROGNOSESICHERHEIT WETTERABLAUF: eher abgesichert\n.\nKOMMENTAR ZUR PROGNOSESICHERHEIT:\nUnklar bleibt, ob es auch ganz im Osten zu Gewitterbildungen kommt.\n.\nDetaillierte Vorhersagen über Höhenwind, Höhentemperaturen und QNH\nentnehmen Sie bitte unseren grafischen Vorhersagekarten.\nDiese Vorhersage wird bei abweichender aktueller Entwicklung nicht\nberichtigt."
}